acache/__init__.py
acache/runners.py
acache/strategy/__init__.py
acache/strategy/base.py
acache/strategy/basic.py
acache/strategy/lru.py
acache/strategy/timed.py
acache/strategy/hash/__init__.py
acache/strategy/hash/md5.py
acache-0.1.3.dist-info/LICENSE
acache-0.1.3.dist-info/METADATA
acache-0.1.3.dist-info/WHEEL
acache-0.1.3.dist-info/top_level.txt
acache-0.1.3.dist-info/zip-safe
acache-0.1.3.dist-info/RECORD
