Metadata-Version: 2.1
Name: acache
Version: 0.1.3
Summary: An extremely versatile and lightweight cache library.
Home-page: UNKNOWN
Author: UNKNOWN
Author-email: UNKNOWN
License: MIT
Platform: UNKNOWN
